jr100emulib/__init__.py
jr100emulib/fskloader.py
jr100emulib-1.0.1.dist-info/LICENSE
jr100emulib-1.0.1.dist-info/METADATA
jr100emulib-1.0.1.dist-info/WHEEL
jr100emulib-1.0.1.dist-info/entry_points.txt
jr100emulib-1.0.1.dist-info/top_level.txt
jr100emulib-1.0.1.dist-info/RECORD
