Metadata-Version: 2.1
Name: jr100emulib
Version: 1.0.1
Summary: 'Support library for JR-100 emulator'
Home-page: https://github.com/kemusiro/jr100emulib
Author: Kenichi Miyata
Author-email: kemusiro@asamomiji.jp
License: MIT
Platform: UNKNOWN
Requires-Dist: numpy (>=1.18.3)
Requires-Dist: scipy
